py_sneakers/__init__.py
py_sneakers/__main__.py
py_sneakers/py_sneakers.py
py_sneakers-1.0.1.dist-info/LICENSE
py_sneakers-1.0.1.dist-info/METADATA
py_sneakers-1.0.1.dist-info/WHEEL
py_sneakers-1.0.1.dist-info/entry_points.txt
py_sneakers-1.0.1.dist-info/top_level.txt
py_sneakers-1.0.1.dist-info/RECORD
