Metadata-Version: 2.1
Name: py-sneakers
Version: 1.0.1
Summary: Python library to emulate the Sneakers effect
Home-page: https://github.com/aenima-x/py-sneakers
Author: Nicolas Rebagliati
Author-email: nicolas.rebagliati@aenima-x.com.ar
License: MIT
Platform: UNKNOWN
Classifier: License :: OSI Approved :: MIT License
Classifier: Programming Language :: Python :: 3
Classifier: Programming Language :: Python :: 3.7
License-File: LICENSE
